tree_sitter_taskjuggler/__init__.pyi
tree_sitter_taskjuggler/py.typed
tree_sitter_taskjuggler/binding.c
tree_sitter_taskjuggler/__init__.py
tree_sitter_taskjuggler/_binding.abi3.so
tree_sitter_taskjuggler-0.1.1.dist-info/WHEEL
tree_sitter_taskjuggler-0.1.1.dist-info/top_level.txt
tree_sitter_taskjuggler-0.1.1.dist-info/METADATA
tree_sitter_taskjuggler-0.1.1.dist-info/RECORD
