Metadata-Version: 2.4
Name: tree-sitter-taskjuggler
Version: 0.1.1
Summary: Treesitter grammar for Taskjuggler Tasks
Author-email: Vijayvithal Jahagirdar <jahagirdar.vs@gmail.com>
License: MIT
Project-URL: Homepage, https://github.com/jahagirdar/taskjuggler-treesitter.git
Keywords: incremental,parsing,tree-sitter,taskjuggler
Classifier: Intended Audience :: Developers
Classifier: Topic :: Software Development :: Compilers
Classifier: Topic :: Text Processing :: Linguistic
Classifier: Typing :: Typed
Requires-Python: >=3.10
Provides-Extra: core
Requires-Dist: tree-sitter~=0.24; extra == "core"
